pronyac/.DS_Store
pronyac/__init__.py
pronyac/c_eigenpair.py
pronyac/con_map.py
pronyac/green_func.py
pronyac/prony_ac.py
pronyac/prony_approx.py
pronyac/spectrum_example.py
pronyac-0.1.0.dist-info/METADATA
pronyac-0.1.0.dist-info/WHEEL
pronyac-0.1.0.dist-info/licenses/LICENSE
pronyac-0.1.0.dist-info/RECORD
