Metadata-Version: 2.1
Name: pronyac
Version: 0.1.0
Summary: A Python program for performing Prony Analytic Continuation (arxiv.org/abs/2312.10576).
Project-URL: Homepage, https://github.com/Green-Phys/PronyAC
Author-email: Lei Zhang <lzphy@umich.edu>
License-File: LICENSE
Classifier: License :: OSI Approved :: MIT License
Classifier: Operating System :: OS Independent
Classifier: Programming Language :: Python :: 3
Requires-Python: >=3.8
